Metadata-Version: 2.1
Name: bike2csv
Version: 0.1.4
Summary: Convert FIT, PWX and TCX files from a bike computer to CSV
Home-page: https://github.com/evavanweenen/bike2csv
Author: Eva van Weenen
Author-email: evanweenen@ethz.ch
License: MIT
Platform: UNKNOWN
